{"armours":{"Bloodfire Gloves":{"name":"Bloodfire Gloves","description":"Arms protection forged from Bloodfire trophies.","icon":"/assets/icons/armours/BloodfireGloves.png","type":"Arms","strength":"Blaze","weakness":"Shock","cells":"Technique","resistance":{"0":78,"1":81,"2":84,"3":87,"4":90,"5":93,"6":96,"7":99,"8":102,"9":105,"10":108},"perks":[{"name":"Evasion","value":1},{"name":"Fireproof","value":1,"from":0,"to":5},{"name":"Fireproof","value":2,"from":6,"to":10}]},"Bloodfire Greaves":{"name":"Bloodfire Greaves","description":"Leg and foot protection forged from Bloodfire trophies.","icon":"/assets/icons/armours/BloodfireGreaves.png","type":"Legs","strength":"Blaze","weakness":"Shock","cells":"Defence","resistance":{"0":78,"1":81,"2":84,"3":87,"4":90,"5":93,"6":96,"7":99,"8":102,"9":105,"10":108},"perks":[{"name":"Evasive Fury","value":1},{"name":"Fireproof","value":1,"from":0,"to":5},{"name":"Fireproof","value":2,"from":6,"to":10}]},"Bloodfire Plate":{"name":"Bloodfire Plate","description":"Torso protection forged from Bloodfire trophies.","icon":"/assets/icons/armours/BloodfirePlate.png","type":"Torso","strength":"Blaze","weakness":"Shock","cells":"Mobility","resistance":{"0":78,"1":81,"2":84,"3":87,"4":90,"5":93,"6":96,"7":99,"8":102,"9":105,"10":108},"perks":[{"name":"Fireproof","value":1},{"name":"Evasion","value":1,"from":0,"to":5},{"name":"Evasion","value":2,"from":6,"to":10}]},"Bloodfire Helm":{"name":"Bloodfire Helm","description":"Head protection forged from Bloodfire trophies.","icon":"/assets/icons/armours/BloodfireHelm.png","type":"Head","strength":"Blaze","weakness":"Shock","cells":"Mobility","resistance":{"0":78,"1":81,"2":84,"3":87,"4":90,"5":93,"6":96,"7":99,"8":102,"9":105,"10":108},"perks":[{"name":"Evasive Fury","value":1},{"name":"Fireproof","value":1,"from":0,"to":5},{"name":"Fireproof","value":2,"from":6,"to":10}]},"Deadeye Boots":{"name":"Deadeye Boots","description":"Leg and foot protection forged from Deadeye trophies.","icon":"/assets/icons/armours/DeadeyeBoots.png","type":"Legs","strength":null,"weakness":null,"cells":"Technique","resistance":{"0":78,"1":81,"2":84,"3":87,"4":90,"5":93,"6":96,"7":99,"8":102,"9":105,"10":108},"perks":[{"name":"Shellshock Resist","value":1},{"name":"Savagery","value":1,"from":0,"to":5},{"name":"Savagery","value":2,"from":6,"to":10}]},"Deadeye Grips":{"name":"Deadeye Grips","description":"Arms protection forged from Deadeye trophies.","icon":"/assets/icons/armours/DeadeyeGrips.png","type":"Arms","strength":null,"weakness":null,"cells":"Technique","resistance":{"0":78,"1":81,"2":84,"3":87,"4":90,"5":93,"6":96,"7":99,"8":102,"9":105,"10":108},"perks":[{"name":"Savagery","value":1},{"name":"Barbed","value":1,"from":0,"to":5},{"name":"Barbed","value":2,"from":6,"to":10}]},"Deadeye Jacket":{"name":"Deadeye Jacket","description":"Torso protection forged from Deadeye trophies.","icon":"/assets/icons/armours/DeadeyeJacket.png","type":"Torso","strength":null,"weakness":null,"cells":"Technique","resistance":{"0":78,"1":81,"2":84,"3":87,"4":90,"5":93,"6":96,"7":99,"8":102,"9":105,"10":108},"perks":[{"name":"Savagery","value":1},{"name":"Shellshock Resist","value":1,"from":0,"to":5},{"name":"Shellshock Resist","value":2,"from":6,"to":10}]},"Deadeye Mask":{"name":"Deadeye Mask","description":"Head protection forged from Deadeye trophies.","icon":"/assets/icons/armours/DeadeyeMask.png","type":"Head","strength":null,"weakness":null,"cells":"Defence","resistance":{"0":78,"1":81,"2":84,"3":87,"4":90,"5":93,"6":96,"7":99,"8":102,"9":105,"10":108},"perks":[{"name":"Barbed","value":1},{"name":"Shellshock Resist","value":1,"from":0,"to":5},{"name":"Shellshock Resist","value":2,"from":6,"to":10}]},"Firebrand Charrhelm":{"name":"Firebrand Charrhelm","description":"Head protection forged from Firebrand trophies.","icon":"/assets/icons/armours/FirebrandCharrhelm.png","type":"Head","strength":"Blaze","weakness":"Frost","cells":"Defence","resistance":{"0":78,"1":81,"2":84,"3":87,"4":90,"5":93,"6":96,"7":99,"8":102,"9":105,"10":108},"perks":[{"name":"Fireproof","value":1},{"name":"Energized","value":1,"from":0,"to":5},{"name":"Energized","value":2,"from":6,"to":10}]},"Firebrand Charrplate":{"name":"Firebrand Charrplate","description":"Torso protection forged from Firebrand trophies.","icon":"/assets/icons/armours/FirebrandCharrplate.png","type":"Torso","strength":"Blaze","weakness":"Frost","cells":"Utility","resistance":{"0":78,"1":81,"2":84,"3":87,"4":90,"5":93,"6":96,"7":99,"8":102,"9":105,"10":108},"perks":[{"name":"Energized","value":1},{"name":"Fireproof","value":1,"from":0,"to":5},{"name":"Fireproof","value":2,"from":6,"to":10}]},"Firebrand Gauntlets":{"name":"Firebrand Gauntlets","description":"Arms protection forged from Firebrand trophies.","icon":"/assets/icons/armours/FirebrandGauntlets.png","type":"Arms","strength":"Blaze","weakness":"Frost","cells":"Utility","resistance":{"0":78,"1":81,"2":84,"3":87,"4":90,"5":93,"6":96,"7":99,"8":102,"9":105,"10":108},"perks":[{"name":"Energized","value":1},{"name":"Rage","value":1,"from":0,"to":5},{"name":"Rage","value":2,"from":6,"to":10}]},"Firebrand Greaves":{"name":"Firebrand Greaves","description":"Leg and foot protection forged from Firebrand trophies.","icon":"/assets/icons/armours/FirebrandGreaves.png","type":"Legs","strength":"Blaze","weakness":"Frost","cells":"Power","resistance":{"0":78,"1":81,"2":84,"3":87,"4":90,"5":93,"6":96,"7":99,"8":102,"9":105,"10":108},"perks":[{"name":"Rage","value":1},{"name":"Fireproof","value":1,"from":0,"to":5},{"name":"Fireproof","value":2,"from":6,"to":10}]},"Frostboots":{"name":"Frostboots","description":"Leg and foot protection forged from Frostback trophies.","icon":"/assets/icons/armours/Frostboots.png","type":"Legs","strength":"Frost","weakness":"Blaze","cells":"Defence","resistance":{"0":78,"1":81,"2":84,"3":87,"4":90,"5":93,"6":96,"7":99,"8":102,"9":105,"10":108},"perks":[{"name":"Fortress","value":1},{"name":"Warmth","value":1,"from":0,"to":5},{"name":"Warmth","value":2,"from":6,"to":10}]},"Frostgrips":{"name":"Frostgrips","description":"Arms protection forged from Frostback trophies.","icon":"/assets/icons/armours/Frostgrips.png","type":"Arms","strength":"Frost","weakness":"Blaze","cells":"Defence","resistance":{"0":78,"1":81,"2":84,"3":87,"4":90,"5":93,"6":96,"7":99,"8":102,"9":105,"10":108},"perks":[{"name":"Warmth","value":1},{"name":"Fortress","value":1,"from":0,"to":5},{"name":"Fortress","value":2,"from":6,"to":10}]},"Frosthelm":{"name":"Frosthelm","description":"Head protection forged from Frostback trophies.","icon":"/assets/icons/armours/Frosthelm.png","type":"Head","strength":"Frost","weakness":"Blaze","cells":"Power","resistance":{"0":78,"1":81,"2":84,"3":87,"4":90,"5":93,"6":96,"7":99,"8":102,"9":105,"10":108},"perks":[{"name":"Knockout King","value":1},{"name":"Warmth","value":1,"from":0,"to":5},{"name":"Warmth","value":2,"from":6,"to":10}]},"Frostplate":{"name":"Frostplate","description":"Torso protection forged from Frostback trophies.","icon":"/assets/icons/armours/Frostplate.png","type":"Torso","strength":"Frost","weakness":"Blaze","cells":"Power","resistance":{"0":78,"1":81,"2":84,"3":87,"4":90,"5":93,"6":96,"7":99,"8":102,"9":105,"10":108},"perks":[{"name":"Fortress","value":1},{"name":"Knockout King","value":1,"from":0,"to":5},{"name":"Knockout King","value":2,"from":6,"to":10}]},"Prismatic Grace":{"name":"Prismatic Grace","description":"Prismatic Grace is a piece of craftable Exotic armour in Dauntless. It is crafted from Rezakiri reagents.","icon":"/assets/icons/armours/PrismaticGrace.png","type":"Head","strength":"Radiant","weakness":"Umbral","cells":"Technique","resistance":{"0":78,"1":81,"2":84,"3":87,"4":90,"5":93,"6":96,"7":99,"8":102,"9":105,"10":108},"unique_effects":[{"name":"PrismaticGraceRevivePrism","description":"After reviving another player, grant them a Radiant Prism that blocks incoming damage for 5 seconds.","value":5},{"name":"PrismaticGraceLethalDamagePrism","description":"The first time you take lethal damage, gain a Radiant Prism that blocks incoming damage for 10 seconds.","value":10},{"name":"PrismaticGraceActivePrismRevive","description":"While active, reviving another player fully restores both players but removes the Prism even at full danger.","value":1}]},"Ragetail Cloak":{"name":"Ragetail Cloak","description":"Torso protection forged from Ragetail trophies.","icon":"/assets/icons/armours/RagetailCloak.png","type":"Torso","strength":null,"weakness":null,"cells":"Defence","resistance":{"0":78,"1":81,"2":84,"3":87,"4":90,"5":93,"6":96,"7":99,"8":102,"9":105,"10":108},"perks":[{"name":"Bloodless","value":1},{"name":"Tough","value":1,"from":0,"to":5},{"name":"Tough","value":2,"from":6,"to":10}]},"Ragetail Grips":{"name":"Ragetail Grips","description":"Arms protection forged from Ragetail trophies.","icon":"/assets/icons/armours/RagetailGrips.png","type":"Arms","strength":null,"weakness":null,"cells":"Power","resistance":{"0":78,"1":81,"2":84,"3":87,"4":90,"5":93,"6":96,"7":99,"8":102,"9":105,"10":108},"perks":[{"name":"Tough","value":1},{"name":"Ragehunter","value":1,"from":0,"to":5},{"name":"Ragehunter","value":2,"from":6,"to":10}]},"Ragetail Touque":{"name":"Ragetail Touque","description":"Head protection forged from Ragetail trophies.","icon":"/assets/icons/armours/RagetailTouque.png","type":"Head","strength":null,"weakness":null,"cells":"Defence","resistance":{"0":78,"1":81,"2":84,"3":87,"4":90,"5":93,"6":96,"7":99,"8":102,"9":105,"10":108},"perks":[{"name":"Tough","value":1},{"name":"Bloodless","value":1,"from":0,"to":5},{"name":"Bloodless","value":2,"from":6,"to":10}]},"Ragetail Treads":{"name":"Ragetail Treads","description":"Leg and foot protection forged from Ragetail trophies.","icon":"/assets/icons/armours/RagetailTreads.png","type":"Legs","strength":null,"weakness":null,"cells":"Power","resistance":{"0":78,"1":81,"2":84,"3":87,"4":90,"5":93,"6":96,"7":99,"8":102,"9":105,"10":108},"perks":[{"name":"Ragehunter","value":1},{"name":"Bloodless","value":1,"from":0,"to":5},{"name":"Bloodless","value":2,"from":6,"to":10}]},"Razorwing Bracers":{"name":"Razorwing Bracers","description":"Arms protection forged from Razorwing trophies.","icon":"/assets/icons/armours/RazorwingBracers.png","type":"Arms","strength":null,"weakness":null,"cells":"Mobility","resistance":{"0":78,"1":81,"2":84,"3":87,"4":90,"5":93,"6":96,"7":99,"8":102,"9":105,"10":108},"perks":[{"name":"Endurance","value":1},{"name":"Bladestorm","value":1,"from":0,"to":5},{"name":"Bladestorm","value":2,"from":6,"to":10}]},"Razorwing Greaves":{"name":"Razorwing Greaves","description":"Leg and foot protection forged from Razorwing trophies.","icon":"/assets/icons/armours/RazorwingGreaves.png","type":"Legs","strength":null,"weakness":null,"cells":"Power","resistance":{"0":78,"1":81,"2":84,"3":87,"4":90,"5":93,"6":96,"7":99,"8":102,"9":105,"10":108},"perks":[{"name":"Bladestorm","value":1},{"name":"Decontruction","value":1,"from":0,"to":5},{"name":"Decontruction","value":2,"from":6,"to":10}]},"Razorwing Helm":{"name":"Razorwing Helm","description":"Head protection forged from Razorwing trophies.","icon":"/assets/icons/armours/RazorwingHelm.png","type":"Head","strength":null,"weakness":null,"cells":"Mobility","resistance":{"0":78,"1":81,"2":84,"3":87,"4":90,"5":93,"6":96,"7":99,"8":102,"9":105,"10":108},"perks":[{"name":"Deconstruction","value":1},{"name":"Endurance","value":1,"from":0,"to":5},{"name":"Endurance","value":2,"from":6,"to":10}]},"Razorwing Plate":{"name":"Razorwing Plate","description":"Torso protection forged from Razorwing trophies.","icon":"/assets/icons/armours/RazorwingPlate.png","type":"Torso","strength":null,"weakness":null,"cells":"Technique","resistance":{"0":78,"1":81,"2":84,"3":87,"4":90,"5":93,"6":96,"7":99,"8":102,"9":105,"10":108},"perks":[{"name":"Deconstruction","value":1},{"name":"Bladestorm","value":1,"from":0,"to":5},{"name":"Bladestorm","value":2,"from":6,"to":10}]},"Reza Greaves":{"name":"Reza Greaves","description":"Leg and foot protection forged from Rezakiri trophies.","icon":"/assets/icons/armours/RezaGreaves.png","type":"Legs","strength":"Radiant","weakness":"Umbral","cells":"Mobility","resistance":{"0":78,"1":81,"2":84,"3":87,"4":90,"5":93,"6":96,"7":99,"8":102,"9":105,"10":108},"perks":[{"name":"Energized","value":1},{"name":"Agility","value":1,"from":0,"to":5},{"name":"Agility","value":2,"from":6,"to":10}]},"Reza Grips":{"name":"Reza Grips","description":"Arms protection forged from Rezakiri trophies.","icon":"/assets/icons/armours/RezaGrips.png","type":"Arms","strength":"Radiant","weakness":"Umbral","cells":"Technique","resistance":{"0":78,"1":81,"2":84,"3":87,"4":90,"5":93,"6":96,"7":99,"8":102,"9":105,"10":108},"perks":[{"name":"Agility","value":1},{"name":"Cunning","value":1,"from":0,"to":5},{"name":"Cunning","value":2,"from":6,"to":10}]},"Reza Helm":{"name":"Reza Helm","description":"Head protection forged from Rezakiri trophies.","icon":"/assets/icons/armours/RezaHelm.png","type":"Head","strength":"Radiant","weakness":"Umbral","cells":"Technique","resistance":{"0":78,"1":81,"2":84,"3":87,"4":90,"5":93,"6":96,"7":99,"8":102,"9":105,"10":108},"perks":[{"name":"Cunning","value":1},{"name":"Energized","value":1,"from":0,"to":5},{"name":"Energized","value":2,"from":6,"to":10}]},"Reza Scales":{"name":"Reza Scales","description":"Torso protection forged from Rezakiri trophies.","icon":"/assets/icons/armours/RezaScales.png","type":"Torso","strength":"Radiant","weakness":"Umbral","cells":"Utility","resistance":{"0":78,"1":81,"2":84,"3":87,"4":90,"5":93,"6":96,"7":99,"8":102,"9":105,"10":108},"perks":[{"name":"Agility","value":1},{"name":"Energized","value":1,"from":0,"to":5},{"name":"Energized","value":2,"from":6,"to":10}]},"Shockjaw Bracers":{"name":"Shockjaw Bracers","description":"Arms protection forged from Shockjaw trophies.","type":"Arms","strength":"Shock","weakness":"Frost","cells":"Utility","resistance":{"0":78,"1":81,"2":84,"3":87,"4":90,"5":93,"6":96,"7":99,"8":102,"9":105,"10":108},"perks":[{"name":"Medic","value":1},{"name":"Aetheric Attunement","value":1,"from":0,"to":5},{"name":"Aetheric Attunement","value":2,"from":6,"to":10}]},"Shockjaw Greaves":{"name":"Shockjaw Greaves","description":"Leg and foot protection forged from Shockjaw trophies.","type":"Legs","strength":"Shock","weakness":"Frost","cells":"Defence","resistance":{"0":78,"1":81,"2":84,"3":87,"4":90,"5":93,"6":96,"7":99,"8":102,"9":105,"10":108},"perks":[{"name":"Insulated","value":1},{"name":"Medic","value":1,"from":0,"to":5},{"name":"Medic","value":2,"from":6,"to":10}]},"Shockjaw Mask":{"name":"Shockjaw Mask","description":"Head protection forged from Shockjaw trophies.","type":"Head","strength":"Shock","weakness":"Frost","cells":"Utility","resistance":{"0":78,"1":81,"2":84,"3":87,"4":90,"5":93,"6":96,"7":99,"8":102,"9":105,"10":108},"perks":[{"name":"Medic","value":1},{"name":"Insulated","value":1,"from":0,"to":5},{"name":"Insulated","value":2,"from":6,"to":10}]},"Shockjaw Vest":{"name":"Shockjaw Vest","description":"Torso protection forged from Shockjaw trophies.","type":"Torso","strength":"Shock","weakness":"Frost","cells":"Defence","resistance":{"0":78,"1":81,"2":84,"3":87,"4":90,"5":93,"6":96,"7":99,"8":102,"9":105,"10":108},"perks":[{"name":"Aetheric Attunement","value":1},{"name":"Insulated","value":1,"from":0,"to":5},{"name":"Insulated","value":2,"from":6,"to":10}]},"Shrowd Boots":{"name":"Shrowd Boots","description":"Leg and foot protection forged from Shrowd trophies.","type":"Legs","strength":"Umbral","weakness":"Radiant","cells":"Utility","resistance":{"0":78,"1":81,"2":84,"3":87,"4":90,"5":93,"6":96,"7":99,"8":102,"9":105,"10":108},"perks":[{"name":"Nine Lives","value":1},{"name":"Medic","value":1,"from":0,"to":5},{"name":"Medic","value":2,"from":6,"to":10}]},"Shrowd Bracers":{"name":"Shrowd Bracers","description":"Arms protection forged from Shrowd trophies.","type":"Arms","strength":"Umbral","weakness":"Radiant","cells":"Utility","resistance":{"0":78,"1":81,"2":84,"3":87,"4":90,"5":93,"6":96,"7":99,"8":102,"9":105,"10":108},"perks":[{"name":"Medic","value":1},{"name":"Rage","value":1,"from":0,"to":5},{"name":"Rage","value":2,"from":6,"to":10}]},"Shrowd Cloak":{"name":"Shrowd Cloak","description":"Torso protection forged from Shrowd trophies.","type":"Torso","strength":"Umbral","weakness":"Radiant","cells":"Power","resistance":{"0":78,"1":81,"2":84,"3":87,"4":90,"5":93,"6":96,"7":99,"8":102,"9":105,"10":108},"perks":[{"name":"Rage","value":1},{"name":"Nine Lives","value":1,"from":0,"to":5},{"name":"Nine Lives","value":2,"from":6,"to":10}]},"Shrowd Hood":{"name":"Shrowd Hood","description":"Head protection forged from Shrowd trophies.","type":"Head","strength":"Umbral","weakness":"Radiant","cells":"Power","resistance":{"0":78,"1":81,"2":84,"3":87,"4":90,"5":93,"6":96,"7":99,"8":102,"9":105,"10":108},"perks":[{"name":"Rage","value":1},{"name":"Medic","value":1,"from":0,"to":5},{"name":"Medic","value":2,"from":6,"to":10}]},"Tragic Echo":{"name":"Tragic Echo","description":"Tragic Echo is a piece of craftable Exotic armour in Dauntless. It is crafted from Shrowd reagents.","icon":"/assets/icons/armours/TragicEcho.png","type":"Head","strength":"Umbral","weakness":"Radiant","cells":"Power","resistance":{"0":78,"1":81,"2":84,"3":87,"4":90,"5":93,"6":96,"7":99,"8":102,"9":105,"10":108},"unique_effects":[{"name":"TragicEchoDamageIncrease","description":"Upon your first death, become a shadow clone that deals 100% increased damage for 15 seconds.","value":2}]}},"behemoths":{},"cells":{"Assassin's Vigour Cell":{"name":"Assassin's Vigour Cell","slot":"Defence","variants":{"+1 Assassin's Vigour Cell":{"rarity":"uncommon","perks":{"Assassin's Vigour":1}},"+2 Assassin's Vigour Cell":{"rarity":"rare","perks":{"Assassin's Vigour":2}},"+3 Assassin's Vigour Cell":{"rarity":"epic","perks":{"Assassin's Vigour":3}}}},"Bloodless Cell":{"name":"Bloodless Cell","slot":"Defence","variants":{"+1 Bloodless Cell":{"rarity":"uncommon","perks":{"Bloodless":1}},"+2 Bloodless Cell":{"rarity":"rare","perks":{"Bloodless":2}},"+3 Bloodless Cell":{"rarity":"epic","perks":{"Bloodless":3}}}},"Fireproof Cell":{"name":"Fireproof Cell","slot":"Defence","variants":{"+1 Fireproof Cell":{"rarity":"uncommon","perks":{"Fireproof":1}},"+2 Fireproof Cell":{"rarity":"rare","perks":{"Fireproof":2}},"+3 Fireproof Cell":{"rarity":"epic","perks":{"Fireproof":3}}}},"Fortress Cell":{"name":"Fortress Cell","slot":"Defence","variants":{"+1 Fortress Cell":{"rarity":"uncommon","perks":{"Fortress":1}},"+2 Fortress Cell":{"rarity":"rare","perks":{"Fortress":2}},"+3 Fortress Cell":{"rarity":"epic","perks":{"Fortress":3}}}},"Insulated Cell":{"name":"Insulated Cell","slot":"Defence","variants":{"+1 Insulated Cell":{"rarity":"uncommon","perks":{"Insulated":1}},"+2 Insulated Cell":{"rarity":"rare","perks":{"Insulated":2}},"+3 Insulated Cell":{"rarity":"epic","perks":{"Insulated":3}}}},"Nine Lives Cell":{"name":"Nine Lives Cell","slot":"Defence","variants":{"+1 Nine Lives Cell":{"rarity":"uncommon","perks":{"Nine Lives":1}},"+2 Nine Lives Cell":{"rarity":"rare","perks":{"Nine Lives":2}},"+3 Nine Lives Cell":{"rarity":"epic","perks":{"Nine Lives":3}}}},"Shellshock Resist Cell":{"name":"Shellshock Resist Cell","slot":"Defence","variants":{"+1 Shellshock Resist Cell":{"rarity":"uncommon","perks":{"Shellshock Resist":1}},"+2 Shellshock Resist Cell":{"rarity":"rare","perks":{"Shellshock Resist":2}},"+3 Shellshock Resist Cell":{"rarity":"epic","perks":{"Shellshock Resist":3}}}},"Sturdy Cell":{"name":"Sturdy Cell","slot":"Defence","variants":{"+1 Sturdy Cell":{"rarity":"uncommon","perks":{"Sturdy":1}},"+2 Sturdy Cell":{"rarity":"rare","perks":{"Sturdy":2}},"+3 Sturdy Cell":{"rarity":"epic","perks":{"Sturdy":3}}}},"Tough Cell":{"name":"Tough Cell","slot":"Defence","variants":{"+1 Tough Cell":{"rarity":"uncommon","perks":{"Tough":1}},"+2 Tough Cell":{"rarity":"rare","perks":{"Tough":2}},"+3 Tough Cell":{"rarity":"epic","perks":{"Tough":3}}}},"Warmth Cell":{"name":"Warmth Cell","slot":"Defence","variants":{"+1 Warmth Cell":{"rarity":"uncommon","perks":{"Warmth":1}},"+2 Warmth Cell":{"rarity":"rare","perks":{"Warmth":2}},"+3 Warmth Cell":{"rarity":"epic","perks":{"Warmth":3}}}},"Agility Cell":{"name":"Agility Cell","slot":"Mobility","variants":{"+1 Agility Cell":{"rarity":"uncommon","perks":{"Agility":1}},"+2 Agility Cell":{"rarity":"rare","perks":{"Agility":2}},"+3 Agility Cell":{"rarity":"epic","perks":{"Agility":3}}}},"Conditioning Cell":{"name":"Conditioning Cell","slot":"Mobility","variants":{"+1 Conditioning Cell":{"rarity":"uncommon","perks":{"Conditioning":1}},"+2 Conditioning Cell":{"rarity":"rare","perks":{"Conditioning":2}},"+3 Conditioning Cell":{"rarity":"epic","perks":{"Conditioning":3}}}},"Endurance Cell":{"name":"Endurance Cell","slot":"Mobility","variants":{"+1 Endurance Cell":{"rarity":"uncommon","perks":{"Endurance":1}},"+2 Endurance Cell":{"rarity":"rare","perks":{"Endurance":2}},"+3 Endurance Cell":{"rarity":"epic","perks":{"Endurance":3}}}},"Evasion Cell":{"name":"Evasion Cell","slot":"Mobility","variants":{"+1 Evasion Cell":{"rarity":"uncommon","perks":{"Evasion":1}},"+2 Evasion Cell":{"rarity":"rare","perks":{"Evasion":2}},"+3 Evasion Cell":{"rarity":"epic","perks":{"Evasion":3}}}},"Fleet Footed Cell":{"name":"Fleet Footed Cell","slot":"Mobility","variants":{"+1 Fleet Footed Cell":{"rarity":"uncommon","perks":{"Fleet Footed":1}},"+2 Fleet Footed Cell":{"rarity":"rare","perks":{"Fleet Footed":2}},"+3 Fleet Footed Cell":{"rarity":"epic","perks":{"Fleet Footed":3}}}},"Nimble Cell":{"name":"Nimble Cell","slot":"Mobility","variants":{"+1 Nimble Cell":{"rarity":"uncommon","perks":{"Nimble":1}},"+2 Nimble Cell":{"rarity":"rare","perks":{"Nimble":2}},"+3 Nimble Cell":{"rarity":"epic","perks":{"Nimble":3}}}},"Swift Cell":{"name":"Swift Cell","slot":"Mobility","variants":{"+1 Swift Cell":{"rarity":"uncommon","perks":{"Swift":1}},"+2 Swift Cell":{"rarity":"rare","perks":{"Swift":2}},"+3 Swift Cell":{"rarity":"epic","perks":{"Swift":3}}}},"Aetherhunter Cell":{"name":"Aetherhunter Cell","slot":"Power","variants":{"+1 Aetherhunter Cell":{"rarity":"uncommon","perks":{"Aetherhunter":1}},"+2 Aetherhunter Cell":{"rarity":"rare","perks":{"Aetherhunter":2}},"+3 Aetherhunter Cell":{"rarity":"epic","perks":{"Aetherhunter":3}}}},"Deconstruction Cell":{"name":"Deconstruction Cell","slot":"Power","variants":{"+1 Deconstruction Cell":{"rarity":"uncommon","perks":{"Deconstruction":1}},"+2 Deconstruction Cell":{"rarity":"rare","perks":{"Deconstruction":2}},"+3 Deconstruction Cell":{"rarity":"epic","perks":{"Deconstruction":3}}}},"Knockout King Cell":{"name":"Knockout King Cell","slot":"Power","variants":{"+1 Knockout King Cell":{"rarity":"uncommon","perks":{"Knockout King":1}},"+2 Knockout King Cell":{"rarity":"rare","perks":{"Knockout King":2}},"+3 Knockout King Cell":{"rarity":"epic","perks":{"Knockout King":3}}}},"Overpower Cell":{"name":"Overpower Cell","slot":"Power","variants":{"+1 Overpower Cell":{"rarity":"uncommon","perks":{"Overpower":1}},"+2 Overpower Cell":{"rarity":"rare","perks":{"Overpower":2}},"+3 Overpower Cell":{"rarity":"epic","perks":{"Overpower":3}}}},"Pacifier Cell":{"name":"Pacifier Cell","slot":"Power","variants":{"+1 Pacifier Cell":{"rarity":"uncommon","perks":{"Pacifier":1}},"+2 Pacifier Cell":{"rarity":"rare","perks":{"Pacifier":2}},"+3 Pacifier Cell":{"rarity":"epic","perks":{"Pacifier":3}}}},"Rage Cell":{"name":"Rage Cell","slot":"Power","variants":{"+1 Rage Cell":{"rarity":"uncommon","perks":{"Rage":1}},"+2 Rage Cell":{"rarity":"rare","perks":{"Rage":2}},"+3 Rage Cell":{"rarity":"epic","perks":{"Rage":3}}}},"Ragehunter Cell":{"name":"Ragehunter Cell","slot":"Power","variants":{"+1 Ragehunter Cell":{"rarity":"uncommon","perks":{"Ragehunter":1}},"+2 Ragehunter Cell":{"rarity":"rare","perks":{"Ragehunter":2}},"+3 Ragehunter Cell":{"rarity":"epic","perks":{"Ragehunter":3}}}},"Sharpened Cell":{"name":"Sharpened Cell","slot":"Power","variants":{"+1 Sharpened Cell":{"rarity":"uncommon","perks":{"Sharpened":1}},"+2 Sharpened Cell":{"rarity":"rare","perks":{"Sharpened":2}},"+3 Sharpened Cell":{"rarity":"epic","perks":{"Sharpened":3}}}},"Acidic Cell":{"name":"Acidic Cell","slot":"Technique","variants":{"+1 Acidic Cell":{"rarity":"uncommon","perks":{"Acidic":1}},"+2 Acidic Cell":{"rarity":"rare","perks":{"Acidic":2}},"+3 Acidic Cell":{"rarity":"epic","perks":{"Acidic":3}}}},"Barbed Cell":{"name":"Barbed Cell","slot":"Technique","variants":{"+1 Barbed Cell":{"rarity":"uncommon","perks":{"Barbed":1}},"+2 Barbed Cell":{"rarity":"rare","perks":{"Barbed":2}},"+3 Barbed Cell":{"rarity":"epic","perks":{"Barbed":3}}}},"Bladestorm Cell":{"name":"Bladestorm Cell","slot":"Technique","variants":{"+1 Bladestorm Cell":{"rarity":"uncommon","perks":{"Bladestorm":1}},"+2 Bladestorm Cell":{"rarity":"rare","perks":{"Bladestorm":2}},"+3 Bladestorm Cell":{"rarity":"epic","perks":{"Bladestorm":3}}}},"Cunning Cell":{"name":"Cunning Cell","slot":"Technique","variants":{"+1 Cunning Cell":{"rarity":"uncommon","perks":{"Cunning":1}},"+2 Cunning Cell":{"rarity":"rare","perks":{"Cunning":2}},"+3 Cunning Cell":{"rarity":"epic","perks":{"Cunning":3}}}},"Evasive Fury Cell":{"name":"Evasive Fury Cell","slot":"Technique","variants":{"+1 Evasive Fury Cell":{"rarity":"uncommon","perks":{"Evasive Fury":1}},"+2 Evasive Fury Cell":{"rarity":"rare","perks":{"Evasive Fury":2}},"+3 Evasive Fury Cell":{"rarity":"epic","perks":{"Evasive Fury":3}}}},"Merciless Cell":{"name":"Merciless Cell","slot":"Technique","variants":{"+1 Merciless Cell":{"rarity":"uncommon","perks":{"Merciless":1}},"+2 Merciless Cell":{"rarity":"rare","perks":{"Merciless":2}},"+3 Merciless Cell":{"rarity":"epic","perks":{"Merciless":3}}}},"Savagery Cell":{"name":"Savagery Cell","slot":"Technique","variants":{"+1 Savagery Cell":{"rarity":"uncommon","perks":{"Savagery":1}},"+2 Savagery Cell":{"rarity":"rare","perks":{"Savagery":2}},"+3 Savagery Cell":{"rarity":"epic","perks":{"Savagery":3}}}},"Weighted Strikes Cell":{"name":"Weighted Strikes Cell","slot":"Technique","variants":{"+1 Weighted Strikes Cell":{"rarity":"uncommon","perks":{"Weighted Strikes":1}},"+2 Weighted Strikes Cell":{"rarity":"rare","perks":{"Weighted Strikes":2}},"+3 Weighted Strikes Cell":{"rarity":"epic","perks":{"Weighted Strikes":3}}}},"Wild Frenzy Cell":{"name":"Wild Frenzy Cell","slot":"Technique","variants":{"+1 Wild Frenzy Cell":{"rarity":"uncommon","perks":{"Wild Frenzy":1}},"+2 Wild Frenzy Cell":{"rarity":"rare","perks":{"Wild Frenzy":2}},"+3 Wild Frenzy Cell":{"rarity":"epic","perks":{"Wild Frenzy":3}}}},"Aetherborne Cell":{"name":"Aetherborne Cell","slot":"Utility","variants":{"+1 Aetherborne Cell":{"rarity":"uncommon","perks":{"Aetherborne":1}},"+2 Aetherborne Cell":{"rarity":"rare","perks":{"Aetherborne":2}},"+3 Aetherborne Cell":{"rarity":"epic","perks":{"Aetherborne":3}}}},"Aetheric Attunement Cell":{"name":"Aetheric Attunement Cell","slot":"Utility","variants":{"+1 Aetheric Attunement Cell":{"rarity":"uncommon","perks":{"Aetheric Attunement":1}},"+2 Aetheric Attunement Cell":{"rarity":"rare","perks":{"Aetheric Attunement":2}},"+3 Aetheric Attunement Cell":{"rarity":"epic","perks":{"Aetheric Attunement":3}}}},"Aetheric Frenzy Cell":{"name":"Aetheric Frenzy Cell","slot":"Utility","variants":{"+1 Aetheric Frenzy Cell":{"rarity":"uncommon","perks":{"Aetheric Frenzy":1}},"+2 Aetheric Frenzy Cell":{"rarity":"rare","perks":{"Aetheric Frenzy":2}},"+3 Aetheric Frenzy Cell":{"rarity":"epic","perks":{"Aetheric Frenzy":3}}}},"Energized Cell":{"name":"Energized Cell","slot":"Utility","variants":{"+1 Energized Cell":{"rarity":"uncommon","perks":{"Energized":1}},"+2 Energized Cell":{"rarity":"rare","perks":{"Energized":2}},"+3 Energized Cell":{"rarity":"epic","perks":{"Energized":3}}}},"Medic Cell":{"name":"Medic Cell","slot":"Utility","variants":{"+1 Medic Cell":{"rarity":"uncommon","perks":{"Medic":1}},"+2 Medic Cell":{"rarity":"rare","perks":{"Medic":2}},"+3 Medic Cell":{"rarity":"epic","perks":{"Medic":3}}}},"Stunning Vigour Cell":{"name":"Stunning Vigour Cell","slot":"Utility","variants":{"+1 Stunning Vigour Cell":{"rarity":"uncommon","perks":{"Stunning Vigour":1}},"+2 Stunning Vigour Cell":{"rarity":"rare","perks":{"Stunning Vigour":2}},"+3 Stunning Vigour Cell":{"rarity":"epic","perks":{"Stunning Vigour":3}}}},"Vampiric Cell":{"name":"Vampiric Cell","slot":"Utility","variants":{"+1 Vampiric Cell":{"rarity":"uncommon","perks":{"Vampiric":1}},"+2 Vampiric Cell":{"rarity":"rare","perks":{"Vampiric":2}},"+3 Vampiric Cell":{"rarity":"epic","perks":{"Vampiric":3}}}}},"lanterns":{"Drasks Fury":{"name":"Drasks Fury","description":null,"cells":"Utility","lantern_ability":{"instant":"Deal 50% increased damage for 6 seconds.","hold":"Fires a lightning bolt in a direction that deals 200 Shock damage multiple times as it passes through a Behemoth."}},"Embermane's Rapture":{"name":"Embermane's Rapture","description":null,"cells":"Utility","lantern_ability":{"instant":"Attack 30% faster for 8 seconds.","hold":"Create a fire ball in front of you that explodes after 5 seconds, dealing 750 Blaze damage to all nearby Behemoths."}},"Pangar's Resolve":{"name":"Pangar's Resolve","description":null,"cells":"Utility","lantern_ability":{"instant":"Restore 25% of your maximum stamina.","hold":"Create a frost pillar in front of you that deals 940 Frost damage to all nearby Behemoths over 12 seconds."}},"Recruit's Lantern":{"name":"Recruit's Lantern","description":null,"cells":"Utility","lantern_ability":{"instant":null,"hold":"Disperses aether that allows the Slayer to track the Behemoth."}},"Shrike's Zeal":{"name":"Shrike's Zeal","description":null,"cells":"Utility","lantern_ability":{"instant":"Move 40% faster for 6 seconds.","hold":"Creates an aura that grants nearby slayers 15% increased movespeed and attack speed for 15 seconds."}},"Skarn's Defiance":{"name":"Skarn's Defiance","description":null,"cells":"Utility","lantern_ability":{"instant":"Grants a 200 hit point shield for 4 seconds.","hold":"Surrounds the slayer in swirling stone that deals 720 damage to all nearby Behemoths over 12 seconds."}}},"perks":{"Acidic":{"name":"Acidic","description":"Increases Wound damage at the cost of Part damage.","key":["part_to_wound_damage","percent_part_damage"],"effects":{"1":{"description":["Converts 30% of Part Damage to Wound Damage",null],"value":[0.3,null]},"2":{"description":["Converts 40% of Part Damage to Wound Damage",null],"value":[0.4,null]},"3":{"description":["Converts 50% of Part Damage to Wound Damage",null],"value":[0.5,null]},"4":{"description":["Converts 50% of Part Damage to Wound Damage","+10% Part damage"],"value":[0.5,1.1]},"5":{"description":["Converts 50% of Part Damage to Wound Damage","+15% Part damage"],"value":[0.5,1.15]},"6":{"description":["Converts 50% of Part Damage to Wound Damage","+20% Part damage"],"value":[0.5,1.2]}}},"Aetherborne":{"name":"Aetherborne","description":"Increases the benefits of using aether vents.","key":["aether_vent_not_used","aether_vent_bonus_heal"],"effects":{"1":{"description":["25% chance not to consume an Aether Vent charge on use","25 additional Aether Vent healing"],"value":[0.25,25]},"2":{"description":["25% chance not to consume an Aether Vent charge on use","50 additional Aether Vent healing"],"value":[0.25,50]},"3":{"description":["25% chance not to consume an Aether Vent charge on use","75 additional Aether Vent healing"],"value":[0.25,75]},"4":{"description":["25% chance not to consume an Aether Vent charge on use","100 additional Aether Vent healing"],"value":[0.25,100]},"5":{"description":["25% chance not to consume an Aether Vent charge on use","150 additional Aether Vent healing"],"value":[0.25,150]},"6":{"description":["25% chance not to consume an Aether Vent charge on use","200 additional Aether Vent healing"],"value":[0.25,200]}}},"Aetherhunter":{"name":"Aetherhunter","description":"Increases damage against aether charged Behemoths.","key":"damage_aether","effects":{"1":{"description":"105% Damage vs Aether-charged Behemoths","value":1.05},"2":{"description":"110% Damage vs Aether-charged Behemoths","value":1.1},"3":{"description":"120% Damage vs Aether-charged Behemoths","value":1.2},"4":{"description":"130% Damage vs Aether-charged Behemoths","value":1.3},"5":{"description":"140% Damage vs Aether-charged Behemoths","value":1.4},"6":{"description":"150% Damage vs Aether-charged Behemoths","value":1.5}}},"Aetheric Attunement":{"name":"Aetheric Attunement","description":"Percent increase to Lantern Charge gained from attacks.","key":"percent_lantern_charge","effects":{"1":{"description":"+10% Lantern Charge","value":1.1},"2":{"description":"+20% Lantern Charge","value":1.2},"3":{"description":"+40% Lantern Charge","value":1.4},"4":{"description":"+60% Lantern Charge","value":1.6},"5":{"description":"+80% Lantern Charge","value":1.8},"6":{"description":"+100% Lantern Charge","value":2}}},"Aetheric Frenzy":{"name":"Aetheric Frenzy","description":"Gains a flat amount of Lantern Charge on each weapon hit.","key":"flat_lantern_charge","effects":{"1":{"description":"+1 Lantern Charge on Hit","value":1},"2":{"description":"+2 Lantern Charge on Hit","value":2},"3":{"description":"+4 Lantern Charge on Hit","value":4},"4":{"description":"+6 Lantern Charge on Hit","value":6},"5":{"description":"+8 Lantern Charge on Hit","value":8},"6":{"description":"+10 Lantern Charge on Hit","value":10}}},"Agility":{"name":"Agility","description":"Reduces the stamina cost of dodging.","key":"dodge_cost_reduction","effects":{"1":{"description":"-10% Dodge Roll Stamina Cost","value":-0.1},"2":{"description":"-20% Dodge Roll Stamina Cost","value":-0.2},"3":{"description":"-30% Dodge Roll Stamina Cost","value":-0.3},"4":{"description":"-40% Dodge Roll Stamina Cost","value":-0.4},"5":{"description":"-55% Dodge Roll Stamina Cost","value":-0.55},"6":{"description":"-70% Dodge Roll Stamina Cost","value":-0.7}}},"Assassin's Vigour":{"name":"Assassin's Vigour","description":"Grants Health after breaking a Behemoth part.","key":"part_break_heal","effects":{"1":{"description":"Heal 50 when you break a part","value":50},"2":{"description":"Heal 100 when you break a part","value":100},"3":{"description":"Heal 150 when you break a part","value":150},"4":{"description":"Heal 200 when you break a part","value":200},"5":{"description":"Heal 250 when you break a part","value":250},"6":{"description":"Heal 300 when you break a part","value":300}}},"Barbed":{"name":"Barbed","description":"Adds a flat amount of Wound damage on hit.","key":["wound_damage","dodge_expose_damage"],"effects":{"1":{"description":["+5 Wound Damage on Hit",null],"value":[5,null]},"2":{"description":["+10 Wound Damage on Hit",null],"value":[10,null]},"3":{"description":["+15 Wound Damage on Hit",null],"value":[15,null]},"4":{"description":["+20 Wound Damage on Hit","After dodging through an attack the next attack's Expose Damage is increased by 200"],"value":[20,200]},"5":{"description":["+30 Wound Damage on Hit","After dodging through an attack the next attack's Expose Damage is increased by 200"],"value":[30,200]},"6":{"description":["+40 Wound Damage on Hit","After dodging through an attack the next attack's Expose Damage is increased by 200"],"value":[40,200]}}},"Bladestorm":{"name":"Bladestorm","description":"Adds a flat amount of Part damage on hit.","key":["flat_part_damage","dodge_part_damage"],"effects":{"1":{"description":["+5 Part Damage on Hit",null],"value":[5,null]},"2":{"description":["+10 Part Damage on Hit",null],"value":[10,null]},"3":{"description":["+15 Part Damage on Hit",null],"value":[15,null]},"4":{"description":["+20 Part Damage on Hit","+200 Part Damage after dodging through an attack"],"value":[20,200]},"5":{"description":["+30 Part Damage on Hit","+200 Part Damage after dodging through an attack"],"value":[30,200]},"6":{"description":["+40 Part Damage on Hit","+200 Part Damage after dodging through an attack"],"value":[40,200]}}},"Bloodless":{"name":"Bloodless","description":"Protects against Wounded and Crippling Wounds statuses.","key":["wound_reduction","crippling_wound_reduction"],"effects":{"1":{"description":["Reduces duration of Wounded status by 50%",null],"value":[-0.5,null]},"2":{"description":["Reduces duration of Wounded status by 80%",null],"value":[-0.8,null]},"3":{"description":["Immune to Wounded status",null],"value":[-1,null]},"4":{"description":["Immune to Wounded status","Reduces effectiveness of Crippling Wounded status by 50%"],"value":[-1,-0.5]},"5":{"description":["Immune to Wounded status","Reduces effectiveness of Crippling Wounded status by 80%"],"value":[-1,-0.8]},"6":{"description":["Immune to Wounded status","Immune to Crippling Wound status"],"value":[-1,-1]}}},"Conditioning":{"name":"Conditioning","description":"Increases Stamina Regen.","key":"stamina_regen","effects":{"1":{"description":"+5 Stamina Regeneration","value":5},"2":{"description":"+10 Stamina Regeneration","value":10},"3":{"description":"+15 Stamina Regeneration","value":15},"4":{"description":"+20 Stamina Regeneration","value":20},"5":{"description":"+25 Stamina Regeneration","value":25},"6":{"description":"+30 Stamina Regeneration","value":30}}},"Cunning":{"name":"Cunning","description":"Grants a chance to deal double damage.","key":"double_damage_chance","effects":{"1":{"description":"1% chance to deal double damage","value":0.01},"2":{"description":"2% chance to deal double damage","value":0.02},"3":{"description":"3% chance to deal double damage","value":0.03},"4":{"description":"5% chance to deal double damage","value":0.05},"5":{"description":"7% chance to deal double damage","value":0.07},"6":{"description":"10% chance to deal double damage","value":0.1}}},"Deconstruction":{"name":"Deconstruction","description":"Bonus damage against objects created by Behemoths.","key":"damage_object","effects":{"1":{"description":"Deal 110% damage to objects created by Behemoths","value":1.1},"2":{"description":"Deal 120% damage to objects created by Behemoths","value":1.2},"3":{"description":"Deal 130% damage to objects created by Behemoths","value":1.3},"4":{"description":"Deal 150% damage to objects created by Behemoths","value":1.5},"5":{"description":"Deal 170% damage to objects created by Behemoths","value":1.7},"6":{"description":"Deal 200% damage to objects created by Behemoths","value":2}}},"Endurance":{"name":"Endurance","description":"Increases Max Stamina.","key":"max_stamina","effects":{"1":{"description":"Increases Max Stamina by 10","value":10},"2":{"description":"Increases Max Stamina by 20","value":20},"3":{"description":"Increases Max Stamina by 40","value":40},"4":{"description":"Increases Max Stamina by 60","value":60},"5":{"description":"Increases Max Stamina by 80","value":80},"6":{"description":"Increases Max Stamina by 100","value":100}}},"Energized":{"name":"Energized","description":"Increase weapon meter gain rate.","key":"weapon_charge_rate","effects":{"1":{"description":"+10% Weapon Charge rate","value":0.1},"2":{"description":"+15% Weapon Charge rate","value":0.15},"3":{"description":"+20% Weapon Charge rate","value":0.2},"4":{"description":"+25% Weapon Charge rate","value":0.25},"5":{"description":"+30% Weapon Charge rate","value":0.3},"6":{"description":"+40% Weapon Charge rate","value":0.4}}},"Evasion":{"name":"Evasion","description":"Increases the time you are invincible when dodging.","key":"iframe_increase","effects":{"1":{"description":"Increases Dodge invulnerability windows by 7%","value":0.07},"2":{"description":"Increases Dodge invulnerability windows by 14%","value":0.14},"3":{"description":"Increases Dodge invulnerability windows by 21%","value":0.21},"4":{"description":"Increases Dodge invulnerability windows by 28%","value":0.28},"5":{"description":"Increases Dodge invulnerability windows by 35%","value":0.35},"6":{"description":"Increases Dodge invulnerability windows by 42%","value":0.42}}},"Evasive Fury":{"name":"Evasive Fury","description":"Temporarily increases attack speed when dodging through a Behemoth's attack.","key":"dodge_attack_speed","effects":{"1":{"description":"4% Attack Speed for 8 seconds after dodging through an attack","value":0.04},"2":{"description":"8% Attack Speed for 8 seconds after dodging through an attack","value":0.08},"3":{"description":"12% Attack Speed for 8 seconds after dodging through an attack","value":0.12},"4":{"description":"16% Attack Speed for 8 seconds after dodging through an attack","value":0.16},"5":{"description":"20% Attack Speed for 8 seconds after dodging through an attack","value":0.2},"6":{"description":"25% Attack Speed for 8 seconds after dodging through an attack","value":0.25}}},"Fireproof":{"name":"Fireproof","description":"Protects against being set on fire.","key":"fire_immunity","effects":{"1":{"description":"Reduces duration of On Fire status by 10%","value":-0.1},"2":{"description":"Reduces duration of On Fire status by 20%","value":-0.2},"3":{"description":"Reduces duration of On Fire status by 40%","value":-0.4},"4":{"description":"Reduces duration of On Fire status by 60%","value":-0.6},"5":{"description":"Reduces duration of On Fire status by 80%","value":-0.8},"6":{"description":"Immune to being set on fire.","value":-1}}},"Fleet Footed":{"name":"Fleet Footed","description":"Temporarily increases Movement Speed after a dodge.","key":"dodge_movement_speed","effects":{"1":{"description":"Following a Dodge, Movement Speed is increased by 10% for 3 seconds","value":1.1},"2":{"description":"Following a Dodge, Movement Speed is increased by 15% for 3 seconds","value":1.15},"3":{"description":"Following a Dodge, Movement Speed is increased by 20% for 3 seconds","value":1.2},"4":{"description":"Following a Dodge, Movement Speed is increased by 25% for 3 seconds","value":1.25},"5":{"description":"Following a Dodge, Movement Speed is increased by 30% for 3 seconds","value":1.3},"6":{"description":"Following a Dodge, Movement Speed is increased by 35% for 3 seconds","value":1.35}}},"Fortress":{"name":"Fortress","description":"Grants a small shield after avoiding damage for a short time.","key":"not_hit_health_shield","effects":{"1":{"description":"Grants a 10 health shield after not getting hit for 10s","value":10},"2":{"description":"Grants a 20 health shield after not getting hit for 10s","value":20},"3":{"description":"Grants a 40 health shield after not getting hit for 10s","value":40},"4":{"description":"Grants a 60 health shield after not getting hit for 10s","value":60},"5":{"description":"Grants a 80 health shield after not getting hit for 10s","value":80},"6":{"description":"Grants a 100 health shield after not getting hit for 10s","value":100}}},"Insulated":{"name":"Insulated","description":"Protects against Shocked status effect and allows you to attack electric shields.","key":["shock_immunity","percent_part_damage"],"effects":{"1":{"description":["Reduces duration of Shocked status by 25%",null],"value":[-0.25,null]},"2":{"description":["Reduces duration of Shocked status by 50%",null],"value":[-0.5,null]},"3":{"description":["Reduces duration of Shocked status by 75%",null],"value":[-0.75,null]},"4":{"description":["Reduces duration of Shocked status by 75%","Reduces knockback and damage of hitting electrified shields"],"value":[-0.75,null]},"5":{"description":["Reduces duration of Shocked status by 75%","Prevents knockback and damage of hitting electrified shields"],"value":[-0.75,null]},"6":{"description":["Immune to Shocked status","Prevents knockback and damage of hitting electrified shields"],"value":[-1,null]}}},"Knockout King":{"name":"Knockout King","description":"Percent increase to Stagger damage.","key":["stagger_damage","dodge_stagger_damage"],"effects":{"1":{"description":["5% Stagger Damage",null],"value":[0.05,null]},"2":{"description":["10% Stagger Damage",null],"value":[0.1,null]},"3":{"description":["15% Stagger Damage",null],"value":[0.15,null]},"4":{"description":["20% Stagger Damage","After dodging through an attack the next weapon attack's Stagger is increased by 50%"],"value":[0.2,0.5]},"5":{"description":["25% Stagger Damage","After dodging through an attack the next weapon attack's Stagger is increased by 50%"],"value":[0.25,0.5]},"6":{"description":["30% Stagger Damage","After dodging through an attack the next weapon attack's Stagger is increased by 100%"],"value":[0.3,1]}}},"Medic":{"name":"Medic","description":"Improves your ability to revive allies.","key":["revive_heal","revive_speed","revive_shield"],"effects":{"1":{"description":["When reviving an ally they are healed an additional 10%",null,null],"value":[1.1,null,null]},"2":{"description":["When reviving an ally they are healed an additional 20%",null,null],"value":[1.2,null,null]},"3":{"description":["When reviving an ally they are healed an additional 30%",null,null],"value":[1.3,null,null]},"4":{"description":["When reviving an ally they are healed an additional 30%","Increases Revive Speed by 66%",null],"value":[1.3,0.66,null]},"5":{"description":["When reviving an ally they are healed an additional 50%","Increases Revive Speed by 66%",null],"value":[1.5,0.66,null]},"6":{"description":["When reviving an ally they are healed an additional 100%","Increases Revive Speed by 66%","Grants a 400 health shield for 20 seconds after reviving an ally"],"value":[2,0.66,400]}}},"Merciless":{"name":"Merciless","description":"Increases Wound damage against staggered Behemoths.","key":"wound_damage","effects":{"1":{"description":"+25 Wound Damage vs Staggered Behemoths","value":25},"2":{"description":"+40 Wound Damage vs Staggered Behemoths","value":40},"3":{"description":"+55 Wound Damage vs Staggered Behemoths","value":55},"4":{"description":"+70 Wound Damage vs Staggered Behemoths","value":70},"5":{"description":"+85 Wound Damage vs Staggered Behemoths","value":85},"6":{"description":"+100 Wound Damage vs Staggered Behemoths","value":100}}},"Nimble":{"name":"Nimble","description":"Restores Stamina when dodging through Behemoth attacks.","key":"dodge_stamina","effects":{"1":{"description":"Gain 10 Stamina after dodging through an attack","value":10},"2":{"description":"Gain 15 Stamina after dodging through an attack","value":15},"3":{"description":"Gain 20 Stamina after dodging through an attack","value":20},"4":{"description":"Gain 25 Stamina after dodging through an attack","value":25},"5":{"description":"Gain 30 Stamina after dodging through an attack","value":30},"6":{"description":"Gain 35 Stamina after dodging through an attack","value":35}}},"Nine Lives":{"name":"Nine Lives","description":"Grants a chance to reduce damage, and later the ability to cheat death.","key":["half_damage","death_heal"],"effects":{"1":{"description":["+5% chance to halve incoming damage",null],"value":[0.05,null]},"2":{"description":["+8% chance to halve incoming damage",null],"value":[0.08,null]},"3":{"description":["+12% chance to halve incoming damage",null],"value":[0.12,null]},"4":{"description":["+12% chance to halve incoming damage","The first time you would be knocked out stay up and heal for 400"],"value":[0.12,400]},"5":{"description":["+16% chance to halve incoming damage","The first time you would be knocked out stay up and heal for 400"],"value":[0.16,400]},"6":{"description":["+20% chance to halve incoming damage","The first time you would be knocked out stay up and heal for 400 and become empowered for 10 seconds"],"value":[0.2,400]}}},"Overpower":{"name":"Overpower","description":"Increases damage against staggered Behemoths.","key":"damage_staggered","effects":{"1":{"description":"110% Damage vs Staggered Behemoths","value":1.1},"2":{"description":"115% Damage vs Staggered Behemoths","value":1.15},"3":{"description":"125% Damage vs Staggered Behemoths","value":1.25},"4":{"description":"140% Damage vs Staggered Behemoths","value":1.4},"5":{"description":"160% Damage vs Staggered Behemoths","value":1.6},"6":{"description":"180% Damage vs Staggered Behemoths","value":1.8}}},"Pacifier":{"name":"Pacifier","description":"Increases stagger damage against enraged Behemoths.","key":"stagger_enraged","effects":{"1":{"description":"110% Stagger vs Enraged Behemoths","value":1.1},"2":{"description":"120% Stagger vs Enraged Behemoths","value":1.2},"3":{"description":"130% Stagger vs Enraged Behemoths","value":1.3},"4":{"description":"140% Stagger vs Enraged Behemoths","value":1.4},"5":{"description":"150% Stagger vs Enraged Behemoths","value":1.5},"6":{"description":"160% Stagger vs Enraged Behemoths","value":1.6}}},"Rage":{"name":"Rage","description":"Increases your damage when your health is low.","key":"low_hp_damage","effects":{"1":{"description":"When under 30% health, deal 105% damage","value":1.05},"2":{"description":"When under 30% health, deal 108% damage","value":1.06},"3":{"description":"When under 30% health, deal 110% damage","value":1.1},"4":{"description":"When under 50% health, deal 115% damage","value":1.15},"5":{"description":"When under 50% health, deal 120% damage","value":1.2},"6":{"description":"When under 50% health, deal 125% damage","value":1.25}}},"Ragehunter":{"name":"Ragehunter","description":"Increases damage against enraged Behemoths.","key":"damage_enraged","effects":{"1":{"description":"105% Damage vs Enraged Behemoths","value":1.05},"2":{"description":"110% Damage vs Enraged Behemoths","value":1.1},"3":{"description":"120% Damage vs Enraged Behemoths","value":1.2},"4":{"description":"130% Damage vs Enraged Behemoths","value":1.3},"5":{"description":"140% Damage vs Enraged Behemoths","value":1.4},"6":{"description":"150% Damage vs Enraged Behemoths","value":1.5}}},"Savagery":{"name":"Savagery","description":"Increases damage against Wounded parts.","key":"damage_wounded","effects":{"1":{"description":"120% Damage vs Wounded Parts","value":1.2},"2":{"description":"130% Damage vs Wounded Parts","value":1.3},"3":{"description":"140% Damage vs Wounded Parts","value":14},"4":{"description":"160% Damage vs Wounded Parts","value":1.6},"5":{"description":"180% Damage vs Wounded Parts","value":1.8},"6":{"description":"200% Damage vs Wounded Parts","value":2}}},"Sharpened":{"name":"Sharpened","description":"Percent increase to Part damage.","key":["percent_part_damage","dodge_percent_part_damage"],"effects":{"1":{"description":["+5% Part Damage",null],"value":[1.05,null]},"2":{"description":["+10% Part Damage",null],"value":[1.1,null]},"3":{"description":["+15% Part Damage",null],"value":[1.15,null]},"4":{"description":["+20% Part Damage","After dodging through an attack the next weapon attack's Part Break Damage is increased by 50%"],"value":[1.2,1.5]},"5":{"description":["+25% Part Damage","After dodging through an attack the next weapon attack's Part Break Damage is increased by 50%"],"value":[1.25,1.5]},"6":{"description":["+30% Part Damage","After dodging through an attack the next weapon attack's Part Break Damage is increased by 100%"],"value":[1.3,2]}}},"Shellshock Resist":{"name":"Shellshock Resist","description":"Protects against the explosion damage and status effect of Shellshock.","key":"shellshock_immunity","effects":{"1":{"description":"Reduces Shell Shocked explosion damage and status effect duration by 10%","value":-0.1},"2":{"description":"Reduces Shell Shocked explosion damage and status effect duration by 20%","value":-0.2},"3":{"description":"Reduces Shell Shocked explosion damage and status effect duration by 40%","value":-0.4},"4":{"description":"Reduces Shell Shocked explosion damage and status effect duration by 60%","value":-0.6},"5":{"description":"Reduces Shell Shocked explosion damage and status effect duration by 80%","value":-0.8},"6":{"description":"Immune to Shell Shocked explosion damage and status effect","value":-1}}},"Stunning Vigour":{"name":"Stunning Vigour","description":"Restores some health whenever a Behemoth is staggered.","key":"stagger_heal","effects":{"1":{"description":"Heal for 50 whenever a Behemoth is Staggered","value":50},"2":{"description":"Heal for 75 whenever a Behemoth is Staggered","value":75},"3":{"description":"Heal for 100 whenever a Behemoth is Staggered","value":100},"4":{"description":"Heal for 125 whenever a Behemoth is Staggered","value":125},"5":{"description":"Heal for 150 whenever a Behemoth is Staggered","value":150},"6":{"description":"Heal for 200 whenever a Behemoth is Staggered","value":200}}},"Sturdy":{"name":"Sturdy","description":"Prevents being staggered on a cooldown.","key":"stagger_prevention","effects":{"1":{"description":"Prevents you from being staggered (120 second cooldown)","value":120},"2":{"description":"Prevents you from being staggered (100 second cooldown)","value":100},"3":{"description":"Prevents you from being staggered (80 second cooldown)","value":80},"4":{"description":"Prevents you from being staggered (60 second cooldown)","value":60},"5":{"description":"Prevents you from being staggered (40 second cooldown)","value":40},"6":{"description":"Prevents you from being staggered (15 second cooldown)","value":15}}},"Swift":{"name":"Swift","description":"Increases Movement Speed when your weapon is sheathed.","key":"sheathed_weapon_movement_speed","effects":{"1":{"description":"While sheathed, increases Movement Speed by 5%","value":1.05},"2":{"description":"While sheathed, increases Movement Speed by 10%","value":1.1},"3":{"description":"While sheathed, increases Movement Speed by 15%","value":1.15},"4":{"description":"While sheathed, increases Movement Speed by 20%","value":1.2},"5":{"description":"While sheathed, increases Movement Speed by 25%","value":1.25},"6":{"description":"While sheathed, increases Movement Speed by 30%, also affects other nearby Slayers.","value":1.3}}},"Tough":{"name":"Tough","description":"Increases Max Health.","key":"max_hp","effects":{"1":{"description":"Increases Max Health by 50","value":50},"2":{"description":"Increases Max Health by 100","value":100},"3":{"description":"Increases Max Health by 150","value":150},"4":{"description":"Increases Max Health by 250","value":250},"5":{"description":"Increases Max Health by 300","value":300},"6":{"description":"Increases Max Health by 500","value":500}}},"Vampiric":{"name":"Vampiric","description":"Restores some health whenever a Behemoth part is Wounded.","key":"wounded_heal","effects":{"1":{"description":"Heal for 50 whenever a Behemoth is Wounded","value":50},"2":{"description":"Heal for 75 whenever a Behemoth is Wounded","value":75},"3":{"description":"Heal for 100 whenever a Behemoth is Wounded","value":100},"4":{"description":"Heal for 125 whenever a Behemoth is Wounded","value":125},"5":{"description":"Heal for 150 whenever a Behemoth is Wounded","value":150},"6":{"description":"Heal for 200 whenever a Behemoth is Wounded","value":200}}},"Warmth":{"name":"Warmth","description":"Protects against Chilled and Frozen status effects.","key":["frozen_immunity","chilled_immunity"],"effects":{"1":{"description":["Reduces duration of Frozen status by 30%",null],"value":[-0.3,null]},"2":{"description":["Reduces duration of Frozen status by 60%",null],"value":[-0.6,null]},"3":{"description":["Immune to being Frozen",null],"value":[-1,null]},"4":{"description":["Immune to being Frozen","Reduces duration of Chilled status by 30%"],"value":[-1,-0.3]},"5":{"description":["Immune to being Frozen","Reduces duration of Chilled status by 60%"],"value":[-1,-0.6]},"6":{"description":["Immune to being Frozen","Immune to being Chilled"],"value":[-1,-1]}}},"Weighted Strikes":{"name":"Weighted Strikes","description":"Adds a flat amount of Stagger damage on hit. At later ranks, allows more weapon attacks to interrupt.","key":["stagger_damage","dpdge_stagger_damage","revive_shield"],"effects":{"1":{"description":["+5 Stagger Damage on Hit",null,null],"value":[5,null,null]},"2":{"description":["+10 Stagger Damage on Hit",null,null],"value":[10,null,null]},"3":{"description":["+15 Stagger Damage on Hit",null,null],"value":[15,null,null]},"4":{"description":["+20 Stagger Damage on Hit","+200 Stagger after dodging through an attack",null],"value":[20,200,null]},"5":{"description":["+30 Stagger Damage on Hit","+200 Stagger after dodging through an attack",null],"value":[30,200,null]},"6":{"description":["+40 Stagger Damage on Hit","+400 Stagger after dodging through an attack","Ranged swings and missiles interrupt unstable Behemoth attacks"],"value":[40,400,null]}}},"Wild Frenzy":{"name":"Wild Frenzy","description":"Increases Attack Speed when at low health.","key":"low_hp_attack_speed","effects":{"1":{"description":"When under 30% health, increase attack speed by 5%","value":1.05},"2":{"description":"When under 30% health, increase attack speed by 8%","value":1.08},"3":{"description":"When under 50% health, increase attack speed by 12%","value":1.12},"4":{"description":"When under 50% health, increase attack speed by 16%","value":1.16},"5":{"description":"When under 50% health, increase attack speed by 20%","value":1.2},"6":{"description":"When under 50% health, increase attack speed by 25%","value":1.25}}}},"weapons":{"Bloodfire Axe":{"name":"Bloodfire Axe","description":"A Slayer's axe forged with Bloodfire trophies.","icon":"/assets/icons/weapons/axe/BloodfireAxe.png","type":"Axe","damage":"Slashing","elemental":"Blaze","cells":["Power","Mobility"],"tier":5,"power":{"0":310,"1":322,"3":346,"4":358,"5":370,"6":382,"7":384,"8":406,"9":418,"10":430},"perks":[{"name":"Wild Frenzy","value":2}],"unique_effects":[{"name":"BloodfireAxeBonusDamage","description":"The fourth hit in quick succession deals 150 bonus damage","value":150},{"name":"BloodfireAxeBonusDamage","description":"The fourth hit in quick succession deals 250 bonus damage","value":250}]},"Deadeye Axe":{"name":"Deadeye Axe","description":"A Slayer's axe forged with Deadeye trophies.","icon":"/assets/icons/weapons/axe/DeadeyeAxe.png","type":"Axe","damage":"Slashing","elemental":null,"cells":["Technique","Defence"],"tier":5,"power":{"0":310,"1":322,"3":346,"4":358,"5":370,"6":382,"7":384,"8":406,"9":418,"10":430},"perks":[{"name":"Acidic","value":1,"from":0,"to":5},{"name":"Acidic","value":2,"from":6,"to":10},{"name":"Savagery","value":2}]},"Firecutter":{"name":"Firecutter","description":"A Slayer's axe forged with Firebrand trophies.","icon":"/assets/icons/weapons/axe/Firecutter.png","type":"Axe","damage":"Cutting","elemental":"Blaze","cells":["Power","Defence"],"tier":5,"power":{"0":310,"1":322,"3":346,"4":358,"5":370,"6":382,"7":384,"8":406,"9":418,"10":430},"perks":[{"name":"Rage","value":2},{"name":"Aetherhunter","value":1,"from":0,"to":5},{"name":"Aetherhunter","value":2,"from":6,"to":10}]},"Frostaxe":{"name":"Frostaxe","description":"A Slayer's axe forged with Frostback trophies.","icon":"/assets/icons/weapons/axe/Frostaxe.png","type":"Axe","damage":"Slashing","elemental":"Frost","cells":["Power","Defence"],"tier":5,"power":{"0":310,"1":322,"3":346,"4":358,"5":370,"6":382,"7":384,"8":406,"9":418,"10":430},"perks":[{"name":"Knockout King","value":1,"from":0,"to":5},{"name":"Knockout King","value":2,"from":6,"to":10},{"name":"Aetherhunter","value":2}]},"Ragecleaver":{"name":"Ragecleaver","description":"A Slayer's axe forged with Ragetail trophies.","icon":"/assets/icons/weapons/axe/Ragecleaver.png","type":"Axe","damage":"Slashing","elemental":null,"cells":["Power","Utility"],"tier":5,"power":{"0":310,"1":322,"3":346,"4":358,"5":370,"6":382,"7":384,"8":406,"9":418,"10":430},"perks":[{"name":"Ragehunter","value":2},{"name":"Pacifier","value":1,"from":0,"to":5},{"name":"Pacifier","value":2,"from":6,"to":10}]},"Razorwing Axe":{"name":"Razorwing Axe","description":"A Slayer's axe forged with Razorwing trophies.","icon":"/assets/icons/weapons/axe/RazorwingAxe.png","type":"Axe","damage":"Slashing","elemental":null,"cells":["Power","Technique"],"tier":5,"power":{"0":310,"1":322,"3":346,"4":358,"5":370,"6":382,"7":384,"8":406,"9":418,"10":430},"perks":[{"name":"Sharpened","value":1,"from":0,"to":5},{"name":"Sharpened","value":2,"from":6,"to":10}],"wip_unique_effects":[{"name":"combo_finisher_bonus_damage","value":200}]},"Rezacutter":{"name":"Rezacutter","description":"A Slayer's axe forged with Rezakiri trophies.","icon":"/assets/icons/weapons/axe/Rezacutter.png","type":"Axe","damage":"Slashing","elemental":"Radiant","cells":["Power","Mobility"],"tier":5,"power":{"0":310,"1":322,"3":346,"4":358,"5":370,"6":382,"7":384,"8":406,"9":418,"10":430},"wip_unique_effects":[{"name":"hit_twice","value":1.05,"from":0,"to":5},{"name":"hit_twice","value":1.1,"from":6,"to":10},{"name":null,"value":null}]},"Shockjaw Scythe":{"name":"Shockjaw Scythe","description":"A Slayer's axe forged with Shockjaw trophies.","type":"Axe","damage":"Slashing","elemental":"Shock","cells":["Power","Utility"],"tier":5,"power":{"0":310,"1":322,"3":346,"4":358,"5":370,"6":382,"7":384,"8":406,"9":418,"10":430},"perks":[{"name":"Energized","value":1,"from":0,"to":5},{"name":"Energized","value":2,"from":6,"to":10}],"wip_unique_effects":[{"name":"vertical_attack_heal","value":200}]},"Shrowd Reaper":{"name":"Shrowd Reaper","description":"A Slayer's axe forged with Shrowd trophies.","type":"Axe","damage":"Slashing","elemental":"Umbral","cells":["Power","Utility"],"tier":5,"power":{"0":310,"1":322,"3":346,"4":358,"5":370,"6":382,"7":384,"8":406,"9":418,"10":430},"perks":[{"name":"Cunning","value":2,"from":0,"to":5},{"name":"Cunning","value":3,"from":6,"to":10}],"wip_unique_effects":[{"name":"low_hp_bonus_damage","value":1.5}]},"Bloodfire Blades":{"name":"Bloodfire Blades","description":"A Slayer's chain blades forged with Bloodfire trophies.","icon":"/assets/icons/weapons/chainblades/BloodfireBlades.png","type":"Chain Blades","damage":"Slashing","elemental":"Blaze","cells":["Technique","Mobility"],"tier":5,"power":{"0":310,"1":322,"3":346,"4":358,"5":370,"6":382,"7":384,"8":406,"9":418,"10":430},"perks":[{"name":"Evasive Fury","value":1,"from":0,"to":5},{"name":"Evasive Fury","value":2,"from":6,"to":10},{"name":"Barbed","value":2}],"unique_effects":[{"name":"BloodfireBladesBonusDamage","description":"The tenth hit in quick succession deals 150 bonus damage","value":150}]},"Deadblades":{"name":"Deadblades","description":"A Slayer's chain blades forged with Deadeye trophies.","icon":"/assets/icons/weapons/chainblades/Deadblades.png","type":"Chain Blades","damage":"Slashing","elemental":null,"cells":["Technique","Defence"],"tier":5,"power":{"0":310,"1":322,"3":346,"4":358,"5":370,"6":382,"7":384,"8":406,"9":418,"10":430},"perks":[{"name":"Acidic","value":1,"from":0,"to":5},{"name":"Acidic","value":2,"from":6,"to":10},{"name":"Barbed","value":2}]},"Fireblades":{"name":"Fireblades","description":"A Slayer's chain blades forged with Firebrand trophies.","icon":"/assets/icons/weapons/chainblades/Fireblades.png","type":"Chain Blades","damage":"Slashing","elemental":"Blaze","cells":["Technique","Utility"],"tier":5,"power":{"0":310,"1":322,"3":346,"4":358,"5":370,"6":382,"7":384,"8":406,"9":418,"10":430},"perks":[{"name":"Aetherhunter","value":1,"from":0,"to":5},{"name":"Aetherhunter","value":2,"from":6,"to":10},{"name":"Rage","value":2}]},"Frostblades":{"name":"Frostblades","description":"A Slayer's chain blades forged with Frostback trophies.","icon":"/assets/icons/weapons/chainblades/Frostblades.png","type":"Chain Blades","damage":"Slashing","elemental":"Frost","cells":["Technique","Defence"],"tier":5,"power":{"0":310,"1":322,"3":346,"4":358,"5":370,"6":382,"7":384,"8":406,"9":418,"10":430},"perks":[{"name":"Weighted Strikes","value":1,"from":0,"to":5},{"name":"Weighted Strikes","value":2,"from":6,"to":10},{"name":"Overpower","value":2}]},"Rageblades":{"name":"Rageblades","description":"A Slayer's chain blades forged with Ragetail trophies.","icon":"/assets/icons/weapons/chainblades/Rageblades.png","type":"Chain Blades","damage":"Slashing","elemental":null,"cells":["Technique","Utility"],"tier":5,"power":{"0":310,"1":322,"3":346,"4":358,"5":370,"6":382,"7":384,"8":406,"9":418,"10":430},"perks":[{"name":"Rage","value":1,"from":0,"to":5},{"name":"Rage","value":2,"from":6,"to":10},{"name":"Ragehunter","value":2}]},"Razorwing Blades":{"name":"Razorwing Blades","description":"A Slayer's chain blades forged with Razorwing trophies.","icon":"/assets/icons/weapons/chainblades/RazorwingsBlades.png","type":"Chain Blades","damage":"Slashing","elemental":null,"cells":["Technique","Mobility"],"tier":5,"power":{"0":310,"1":322,"3":346,"4":358,"5":370,"6":382,"7":384,"8":406,"9":418,"10":430},"perks":[{"name":"Sharpened","value":1,"from":0,"to":5},{"name":"Sharpened","value":2,"from":6,"to":10},{"name":"Bladestorm","value":2}]},"Rezakiri's Fangs":{"name":"Rezakiri's Fangs","description":"A Slayer's chain blades forged with Rezakiri trophies.","icon":"/assets/icons/weapons/chainblades/Rezakiri'sFangs.png","type":"Chain Blades","damage":"Slashing","elemental":"Radiant","cells":["Technique","Power"],"tier":5,"power":{"0":310,"1":322,"3":346,"4":358,"5":370,"6":382,"7":384,"8":406,"9":418,"10":430},"wip_unique_effects":[{"name":"hit_twice","value":1.05,"from":0,"to":5},{"name":"hit_twice","value":1.1,"from":6,"to":10},{"name":"seven_hit_part_damage","value":3}]},"Shockjaw Blades":{"name":"Shockjaw Blades","description":"A Slayer's chain blades forged with Shockjaw trophies.","type":"Chain Blades","damage":"Slashing","elemental":"Shock","cells":["Technique","Utility"],"tier":5,"power":{"0":310,"1":322,"3":346,"4":358,"5":370,"6":382,"7":384,"8":406,"9":418,"10":430},"perks":[{"name":"Energized","value":1,"from":0,"to":5},{"name":"Energized","value":2,"from":6,"to":10}],"wip_unique_effects":[{"name":"lifesteal_wounded_parts","value":1.05}]},"Shrowd Blades":{"name":"Shrowd Blades","description":"A Slayer's chain blades forged with Shrowd trophies.","type":"Chain Blades","damage":"Slashing","elemental":"Umbral","cells":["Technique","Utility"],"tier":5,"power":{"0":310,"1":322,"3":346,"4":358,"5":370,"6":382,"7":384,"8":406,"9":418,"10":430},"perks":[{"name":"Cunning","value":2,"from":0,"to":5},{"name":"Cunning","value":3,"from":6,"to":10}],"wip_unique_effects":[{"name":"low_hp_bonus_damage","value":1.5}]},"Bloodfire Hammer":{"name":"Bloodfire Hammer","description":"A Slayer's hammer forged with Bloodfire trophies.","icon":"/assets/icons/weapons/hammer/BloodfireHammer.png","type":"Hammer","damage":"Blunt","elemental":"Blaze","cells":["Power","Mobility"],"tier":5,"power":{"0":310,"1":322,"3":346,"4":358,"5":370,"6":382,"7":384,"8":406,"9":418,"10":430},"unique_effects":[{"name":"BloodfireHammerAttackSpeed","description":"+25% Attack Speed for 8 seconds after landing a Hammer Blast","value":1.25},{"name":"BloodfireHammerStaggerDamage","description":"The fifth hit in a row deals +100% Stagger damage","value":2}]},"Deadeye Hammer":{"name":"Deadeye Hammer","description":"A Slayer's hammer forged with Deadeye trophies.","icon":"/assets/icons/weapons/hammer/DeadeyeHammer.png","type":"Hammer","damage":"Blunt","elemental":null,"cells":["Power","Defence"],"tier":5,"power":{"0":310,"1":322,"3":346,"4":358,"5":370,"6":382,"7":384,"8":406,"9":418,"10":430},"perks":[{"name":"Savagery","value":2},{"name":"Acidic","value":1,"from":0,"to":5},{"name":"Acidic","value":2,"from":6,"to":10}]},"Firemace":{"name":"Firemace","description":"A Slayer's hammer forged with Firebrand trophies.","icon":"/assets/icons/weapons/hammer/Firemace.png","type":"Hammer","damage":"Blunt","elemental":"Blaze","cells":["Power","Defence"],"tier":5,"power":{"0":310,"1":322,"3":346,"4":358,"5":370,"6":382,"7":384,"8":406,"9":418,"10":430},"perks":[{"name":"Aetherhunter","value":1,"from":0,"to":5},{"name":"Aetherhunter","value":2,"from":6,"to":10},{"name":"Rage","value":2}]},"Frostmaul":{"name":"Frostmaul","description":"A Slayer's hammer forged with Frostback trophies.","icon":"/assets/icons/weapons/hammer/Frostmaul.png","type":"Hammer","damage":"Blunt","elemental":"Frost","cells":["Power","Defence"],"tier":5,"power":{"0":310,"1":322,"3":346,"4":358,"5":370,"6":382,"7":384,"8":406,"9":418,"10":430},"perks":[{"name":"Aetherhunter","value":2},{"name":"Knockout King","value":1,"from":0,"to":5},{"name":"Knockout King","value":2,"from":6,"to":10}]},"Ragehammer":{"name":"Ragehammer","description":"A Slayer's hammer forged with Ragetail trophies.","icon":"/assets/icons/weapons/hammer/Ragehammer.png","type":"Hammer","damage":"Blunt","elemental":null,"cells":["Power","Utility"],"tier":5,"power":{"0":310,"1":322,"3":346,"4":358,"5":370,"6":382,"7":384,"8":406,"9":418,"10":430},"perks":[{"name":"Pacifier","value":1,"from":0,"to":5},{"name":"Pacifier","value":2,"from":6,"to":10},{"name":"Ragehunter","value":2}]},"Razorwing Hammer":{"name":"Razorwing Hammer","description":"A Slayer's hammer forged with Razorwing trophies.","icon":"/assets/icons/weapons/hammer/RazorwingHammer.png","type":"Hammer","damage":"Blunt","elemental":null,"cells":["Technique","Power"],"tier":5,"power":{"0":310,"1":322,"3":346,"4":358,"5":370,"6":382,"7":384,"8":406,"9":418,"10":430},"perks":[{"name":"Sharpened","value":1,"from":0,"to":5},{"name":"Sharpened","value":2,"from":6,"to":10}],"wip_unique_effects":[{"name":"stamina_on_reload","value":30}]},"Rezacrusher":{"name":"Rezacrusher","description":"A Slayer's hammer forged with Rezakiri trophies.","icon":"/assets/icons/weapons/hammer/Rezacrusher.png","type":"Hammer","damage":"Blunt","elemental":"Radiant","cells":["Power","Mobility"],"tier":5,"power":{"0":310,"1":322,"3":346,"4":358,"5":370,"6":382,"7":384,"8":406,"9":418,"10":430},"wip_unique_effects":[{"name":null,"value":null},{"name":"hit_twice","value":1.05,"from":0,"to":5},{"name":"hit_twice","value":1.1,"from":6,"to":10}]},"Shockjaw Smasher":{"name":"Shockjaw Smasher","description":"A Slayer's hammer forged with Shockjaw trophies.","type":"Hammer","damage":"Blunt","elemental":"Shock","cells":["Power","Utility"],"tier":5,"power":{"0":310,"1":322,"3":346,"4":358,"5":370,"6":382,"7":384,"8":406,"9":418,"10":430},"perks":[{"name":"Conditioning","value":1,"from":0,"to":5},{"name":"Conditioning","value":2,"from":6,"to":10}],"wip_unique_effects":[{"name":"heal_on_behemoth_stagger","value":300}]},"Shrowdmaul":{"name":"Shrowdmaul","description":"A Slayer's hammer forged with Shrowd trophies.","type":"Hammer","damage":"Blunt","elemental":"Umbral","cells":["Power","Utility"],"tier":5,"power":{"0":310,"1":322,"3":346,"4":358,"5":370,"6":382,"7":384,"8":406,"9":418,"10":430},"perks":[{"name":"Cunning","value":2,"from":0,"to":5},{"name":"Cunning","value":3,"from":6,"to":10}],"wip_unique_effects":[{"name":"low_hp_bonus_damage","value":1.5}]},"Bloodfire Saber":{"name":"Bloodfire Saber","description":"A Slayer's sword forged with Bloodfire trophies.","icon":"/assets/icons/weapons/swords/BloodfireSaber.png","type":"Sword","damage":"Slashing","elemental":"Blaze","cells":["Technique","Mobility"],"tier":5,"power":{"0":310,"1":322,"3":346,"4":358,"5":370,"6":382,"7":384,"8":406,"9":418,"10":430},"perks":[{"name":"Wild Frenzy","value":2,"from":0,"to":5},{"name":"Wild Frenzy","value":3,"from":6,"to":10}],"unique_effects":[{"name":"BloodfireSaberPartDamage","discription":"The seventh hit in a row deals +200% part damage","value":3,"from":0,"to":5},{"name":"BloodfireSaberPartDamage","description":"The seventh hit in a row deals +250% part damage","value":5.5,"from":6,"to":10}]},"Deadeye Ripper":{"name":"Deadeye Ripper","description":"A Slayer's sword forged with Deadeye trophies.","icon":"/assets/icons/weapons/swords/DeadeyeRipper.png","type":"Sword","damage":"Slashing","elemental":null,"cells":["Technique","Defence"],"tier":5,"power":{"0":310,"1":322,"3":346,"4":358,"5":370,"6":382,"7":384,"8":406,"9":418,"10":430},"perks":[{"name":"Barbed","value":2},{"name":"Acidic","value":1,"from":0,"to":5},{"name":"Acidic","value":2,"from":6,"to":10}]},"Firesaber":{"name":"Firesaber","description":"A Slayer's sword forged with Firebrand trophies.","icon":"/assets/icons/weapons/swords/Firesaber.png","type":"Sword","damage":"Cutting","elemental":"Blaze","cells":["Power","Defence"],"tier":5,"power":{"0":310,"1":322,"3":346,"4":358,"5":370,"6":382,"7":384,"8":406,"9":418,"10":430},"perks":[{"name":"Rage","value":2},{"name":"Aetherhunter","value":1,"from":0,"to":5},{"name":"Aetherhunter","value":2,"from":6,"to":10}]},"Frostsaber":{"name":"Frostsaber","description":"A Slayer's sword forged with Frostback trophies.","icon":"/assets/icons/weapons/swords/Frostsaber.png","type":"Sword","damage":"Slashing","elemental":"Frost","cells":["Power","Defence"],"tier":5,"power":{"0":310,"1":322,"3":346,"4":358,"5":370,"6":382,"7":384,"8":406,"9":418,"10":430},"perks":[{"name":"Aetherhunter","value":2},{"name":"Knockout King","value":1,"from":0,"to":5},{"name":"Knockout King","value":2,"from":6,"to":10}]},"Ragesaber":{"name":"Ragesaber","description":"A Slayer's sword forged with Ragetail trophies.","icon":"/assets/icons/weapons/swords/Ragesaber.png","type":"Sword","damage":"Slashing","elemental":null,"cells":["Utility","Defence"],"tier":5,"power":{"0":310,"1":322,"3":346,"4":358,"5":370,"6":382,"7":384,"8":406,"9":418,"10":430},"perks":[{"name":"Ragehunter","value":2},{"name":"Rage","value":1,"from":0,"to":5},{"name":"Rage","value":2,"from":6,"to":10}]},"Razorwing Sword":{"name":"Razorwing Sword","description":"A Slayer's sword forged with Razorwing trophies.","icon":"/assets/icons/weapons/swords/RazorwingSword.png","type":"Sword","damage":"Slashing","elemental":null,"cells":["Technique","Mobility"],"tier":5,"power":{"0":310,"1":322,"3":346,"4":358,"5":370,"6":382,"7":384,"8":406,"9":418,"10":430},"perks":[{"name":"Bladestorm","value":2},{"name":"Sharpened","value":1,"from":0,"to":5},{"name":"Sharpened","value":2,"from":6,"to":10}]},"Rezakatana":{"name":"Rezakatana","description":"A Slayer's sword forged with Rezakiri trophies.","icon":"/assets/icons/weapons/swords/Rezakatana.png","type":"Sword","damage":"Slashing","elemental":"Radiant","cells":["Technique","Utility"],"tier":5,"power":{"0":310,"1":322,"3":346,"4":358,"5":370,"6":382,"7":384,"8":406,"9":418,"10":430},"wip_unique_effects":[{"name":"hit_twice","value":1.05,"from":0,"to":5},{"name":"hit_twice","value":1.1,"from":6,"to":10},{"name":"bonus_part_damage","value":3}]},"Shockjaw Sword":{"name":"Shockjaw Sword","description":"A Slayer's sword forged with Shockjaw trophies.","type":"Sword","damage":"Slashing","elemental":"Shock","cells":["Utility","Mobility"],"tier":5,"power":{"0":310,"1":322,"3":346,"4":358,"5":370,"6":382,"7":384,"8":406,"9":418,"10":430},"perks":[{"name":"Energized","value":1,"from":0,"to":5},{"name":"Energized","value":2,"from":6,"to":10}],"wip_unique_effects":[{"name":"lifesteal_wounded_parts","value":1.05}]},"Shrowd Slicer":{"name":"Shrowd Slicer","description":"A Slayer's sword forged with Shrowd trophies.","type":"Sword","damage":"Slashing","elemental":"Umbral","cells":["Power","Utility"],"tier":5,"power":{"0":310,"1":322,"3":346,"4":358,"5":370,"6":382,"7":384,"8":406,"9":418,"10":430},"perks":[{"name":"Cunning","value":2,"from":0,"to":5},{"name":"Cunning","value":3,"from":6,"to":10}],"wip_unique_effects":[{"name":"low_hp_bonus_damage","value":1.5}]},"The Hunger":{"name":"The Hunger","description":"The Hunger is a craftable Exotic weapon in Dauntless. It is crafted from Shrowd reagents.","icon":"/assets/icons/weapons/swords/TheHunger.png","type":"Sword","damage":"Slashing","elemental":"Umbral","cells":["Power","Utility"],"tier":5,"power":{"0":310,"1":322,"3":346,"4":358,"5":370,"6":382,"7":384,"8":406,"9":418,"10":430},"unique_effects":[{"name":"HungerDamageIncreaseMeter","description":"Deal up to 25% increased damage as your meter increases.","value":1.25},{"name":"HungerDamageIncreaseFeast","description":"Activate at max meter to enter Feast, dealing 75% increased damage for 15 seconds, but taking damage after each hit.","value":1.75},{"name":"HungerRegainHealth","description":"Activate again during Feast to unleash an Umbral attack that can regain lost health."}]},"Bloodfire Pike":{"name":"Bloodfire Pike","description":"A Slayer's war pike forged with Bloodfire trophies.","icon":"/assets/icons/weapons/warpike/BloodfirePike.png","type":"War Pike","damage":"Piercing","elemental":"Blaze","cells":["Technique","Mobility"],"tier":5,"power":{"0":310,"1":322,"3":346,"4":358,"5":370,"6":382,"7":384,"8":406,"9":418,"10":430},"unique_effects":[{"name":"BloodfirePikeAttackSpeed","description":"+30% Attack Speed for 4-10 seconds after hitting with a Special Attack missile. Duration depends on missile strength.","value":1.3},{"name":"BloodfirePikeWoundDamage","description":"The seventh hit in a row deals +200 Wound damage.","value":200,"from":0,"to":5},{"name":"BloodfirePikeWoundDamage","description":"The seventh hit in a row deals +300 Wound damage.","value":200,"from":6,"to":10}]},"Deadeye Pike":{"name":"Deadeye Pike","description":"A Slayer's war pike forged with Deadeye trophies.","icon":"/assets/icons/weapons/warpike/DeadeyePike.png","type":"War Pike","damage":"Piercing","elemental":null,"cells":["Technique","Defence"],"tier":5,"power":{"0":310,"1":322,"3":346,"4":358,"5":370,"6":382,"7":384,"8":406,"9":418,"10":430},"perks":[{"name":"Acidic","value":1,"from":0,"to":5},{"name":"Acidic","value":2,"from":6,"to":10},{"name":"Barbed","value":2}]},"Firepike":{"name":"Firepike","description":"A Slayer's war pike forged with Firebrand trophies.","icon":"/assets/icons/weapons/warpike/Firepike.png","type":"War Pike","damage":"Piercing","elemental":"Blaze","cells":["Power","Utility"],"tier":5,"power":{"0":310,"1":322,"3":346,"4":358,"5":370,"6":382,"7":384,"8":406,"9":418,"10":430},"perks":[{"name":"Aetherhunter","value":1,"from":0,"to":5},{"name":"Aetherhunter","value":2,"from":6,"to":10},{"name":"Rage","value":2}]},"Frostpike":{"name":"Frostpike","description":"A Slayer's war pike forged with Frostback trophies.","icon":"/assets/icons/weapons/warpike/Frostpike.png","type":"War Pike","damage":"Piercing","elemental":"Frost","cells":["Technique","Defence"],"tier":5,"power":{"0":310,"1":322,"3":346,"4":358,"5":370,"6":382,"7":384,"8":406,"9":418,"10":430},"perks":[{"name":"Weighted Strikes","value":1,"from":0,"to":5},{"name":"Weighted Strikes","value":2,"from":6,"to":10},{"name":"Aetherhunter","value":2}]},"Ragepike":{"name":"Ragepike","description":"A Slayer's war pike forged with Ragetail trophies.","icon":"/assets/icons/weapons/warpike/Ragepike.png","type":"War Pike","damage":"Piercing","elemental":null,"cells":["Technique","Utility"],"tier":5,"power":{"0":310,"1":322,"3":346,"4":358,"5":370,"6":382,"7":384,"8":406,"9":418,"10":430},"perks":[{"name":"Rage","value":1,"from":0,"to":5},{"name":"Rage","value":2,"from":6,"to":10},{"name":"Ragehunter","value":2}]},"Razorwing Pike":{"name":"Razorwing Pike","description":"A Slayer's war pike forged with Razorwing trophies.","icon":"/assets/icons/weapons/warpike/RazorwingPike.png","type":"War Pike","damage":"Piercing","elemental":null,"cells":["Technique","Mobility"],"tier":5,"power":{"0":310,"1":322,"3":346,"4":358,"5":370,"6":382,"7":384,"8":406,"9":418,"10":430},"perks":[{"name":"Sharpened","value":1,"from":0,"to":5},{"name":"Sharpened","value":2,"from":6,"to":10},{"name":"Bladestorm","value":2}]},"Rezakiller":{"name":"Rezakiller","description":"A Slayer's war pike forged with Rezakiri trophies.","icon":"/assets/icons/weapons/warpike/Rezakiller.png","type":"War Pike","damage":"Piercing","elemental":"Radiant","cells":["Technique","Power"],"tier":5,"power":{"0":310,"1":322,"3":346,"4":358,"5":370,"6":382,"7":384,"8":406,"9":418,"10":430},"wip_unique_effects":[{"name":"hit_twice","value":1.05,"from":0,"to":5},{"name":"hit_twice","value":1.1,"from":6,"to":10},{"name":"seventh_hit_wound_damage","value":200}]},"Shockjaw Pike":{"name":"Shockjaw Pike","description":"A Slayer's war pike forged with Shockjaw trophies.","type":"War Pike","damage":"Piercing","elemental":"Shock","cells":["Utility","Technique"],"tier":5,"power":{"0":310,"1":322,"3":346,"4":358,"5":370,"6":382,"7":384,"8":406,"9":418,"10":430},"perks":[{"name":"Energized","value":1,"from":0,"to":5},{"name":"Energized","value":2,"from":6,"to":10}],"wip_unique_effects":[{"name":"lifesteal_wounded_parts","value":1.05}]},"Shrowdpike":{"name":"Shrowdpike","description":"A Slayer's war pike forged with Shrowd trophies.","type":"War Pike","damage":"Piercing","elemental":"Umbral","cells":["Technique","Utility"],"tier":5,"power":{"0":310,"1":322,"3":346,"4":358,"5":370,"6":382,"7":384,"8":406,"9":418,"10":430},"perks":[{"name":"Cunning","value":2,"from":0,"to":5},{"name":"Cunning","value":3,"from":6,"to":10}],"wip_unique_effects":[{"name":"low_hp_bonus_damage","value":1.5}]},"The Godhand":{"name":"The Godhand","description":"The Godhand is a craftable Exotic weapon in Dauntless. It is crafted from Rezakiri reagents.","type":"War Pike","damage":"Piercing","elemental":"Radiant","cells":["Power","Technique"],"tier":5,"power":{"0":310,"1":322,"3":346,"4":358,"5":370,"6":382,"7":384,"8":406,"9":418,"10":430},"wip_unique_effects":[{"name":"beam_meter_damage","value":3}]}}}